emblematic/__init__.py
emblematic/__main__.py
emblematic/cli/__init__.py
emblematic/cli/argopts.py
emblematic/cli/commands.py
emblematic/cli/files.py
emblematic/composition.py
emblematic/svg.py
emblematic-4.2.2.dist-info/METADATA
emblematic-4.2.2.dist-info/WHEEL
emblematic-4.2.2.dist-info/entry_points.txt
emblematic-4.2.2.dist-info/licenses/LICENSE.txt
emblematic-4.2.2.dist-info/RECORD
