Metadata-Version: 2.4
Name: emblematic
Version: 4.2.2
Summary: Generate emblems from an icon and a background
License-Expression: EUPL-1.2
License-File: LICENSE.txt
Keywords: icon,avatar,emblem,logo,symbol
Author: Stefano Pigozzi
Author-email: me@steffo.eu
Maintainer: Stefano Pigozzi
Maintainer-email: me@steffo.eu
Requires-Python: >=3.11,<4.0
Classifier: Programming Language :: Python :: 3
Classifier: Programming Language :: Python :: 3.11
Classifier: Development Status :: 3 - Alpha
Classifier: Environment :: Console
Classifier: License :: OSI Approved :: European Union Public Licence 1.2 (EUPL 1.2)
Classifier: Topic :: Multimedia :: Graphics
Classifier: Typing :: Typed
Requires-Dist: beautifulsoup4 (>=4.12.3,<5.0.0)
Requires-Dist: click (>=8.1.7,<9.0.0)
Requires-Dist: lxml (>=5.2.1,<7.0.0)
Project-URL: Documentation, https://artifacts.steffo.eu/steffo/emblematic/
Project-URL: Issues, https://forge.steffo.eu/steffo/emblematic/issues
Project-URL: Source, https://forge.steffo.eu/steffo/emblematic
